hpyrust_text-0.1.5.dist-info/METADATA
hpyrust_text-0.1.5.dist-info/WHEEL
hpyrust_text/__init__.py
hpyrust_text/hpyrust_text.cpython-312-darwin.so
hpyrust_text-0.1.5.dist-info/RECORD
